youtubeCommentScrapper/__init__.py
youtubeCommentScrapper-0.0.1.dist-info/License.txt
youtubeCommentScrapper-0.0.1.dist-info/METADATA
youtubeCommentScrapper-0.0.1.dist-info/WHEEL
youtubeCommentScrapper-0.0.1.dist-info/top_level.txt
youtubeCommentScrapper-0.0.1.dist-info/RECORD
